Year 2/DSD Lab/week6/lab5p4.v
module dec2to4(w, y, e);
   input [1:0]w;
   input e;
   output reg [0:3]y;
   always @(e, w)
   begin
      y = 4'b0000;
      if(w==2'b00&e==1)
         y[0] = 1;
      else if(w==2'b01&e==1)
      	      y[1] = 1;
      	   else if(w==2'b10&e==1) 
      	   	   y[2] = 1;
      	   	else if(w==2'b11&e==1)
      	   		y[3] = 1;
   end
endmodule

module lab5p4(W, f);
   input [2:0]W;
   output f;
   wire [0:7]M;
   dec2to4 st0(W[1:0], M[0:3], ~W[2]);
   dec2to4 st1(W[1:0], M[4:7], W[2]);
   assign f = M[3]|M[5]|M[6]|M[7]; 
endmodule

Year 2/DSD Lab/week6/lab5p4_tb.v
`timescale 1ns/1ns
`include "lab5p4.v"

module lab5p4_tb;
reg [2:0]W;
wire f;

lab5p4 wf(W, f);
initial begin
	
	$dumpfile("lab5p4_tb.vcd");
	$dumpvars(0, lab5p4_tb);
	
	W = 3'b000;
	#20;
	
	W = 3'b001;
	#20;
	
	W = 3'b010;
	#20;
	
	W = 3'b011;
	#20;
	
	W = 3'b100;
	#20;
	
	W = 3'b101;
	#20;
	
	W = 3'b110;
	#20;
	
	W = 3'b111;
	#20;
	
	$display("Test Complete");
	$finish;
end
endmodule

Year 2/DSD Lab/week6/lab5p4_tb.vcd
$date
	Mon Sep  4 15:23:17 2023
$end
$version
	Icarus Verilog
$end
$timescale
	1ns
$end
$scope module lab5p4_tb $end
$var wire 1 ! f $end
$var reg 3 " W [2:0] $end
$scope module wf $end
$var wire 3 # W [2:0] $end
$var wire 1 ! f $end
$var wire 8 $ M [0:7] $end
$scope module st0 $end
$var wire 1 % e $end
$var wire 2 & w [1:0] $end
$var reg 4 ' y [0:3] $end
$upscope $end
$scope module st1 $end
$var wire 1 ( e $end
$var wire 2 ) w [1:0] $end
$var reg 4 * y [0:3] $end
$upscope $end
$upscope $end
$upscope $end
$enddefinitions $end
#0
$dumpvars
b0 *
b0 )
0(
b1000 '
b0 &
1%
b10000000 $
b0 #
b0 "
0!
$end
#20
b1000000 $
b100 '
b1 &
b1 )
b1 "
b1 #
#40
b100000 $
b10 '
b10 &
b10 )
b10 "
b10 #
#60
1!
b10000 $
b1 '
b11 &
b11 )
b11 "
b11 #
#80
0!
b0 '
0%
b1000 $
b1000 *
b0 &
b0 )
1(
b100 "
b100 #
#100
1!
b100 $
b100 *
b1 &
b1 )
b101 "
b101 #
#120
b10 $
b10 *
b10 &
b10 )
b110 "
b110 #
#140
b1 $
b1 *
b11 &
b11 )
b111 "
b111 #
