Year 2/DSD Lab/week6/lab5p2.v
module mux8to1(s,w,f);
   input [2:0]s;
   input [0:7]w;
   output reg f;
   always @(s,w)
   begin
      case(s)
         0: f=w[0];
         1: f=w[1];
         2: f=w[2];
         3: f=w[3];
         4: f=w[4];
         5: f=w[5];
         6: f=w[6];
         7: f=w[7];
         default: f=0;
      endcase
   end
endmodule

module lab5p2(G,B);
   input [3:0]G;
   output [3:0]B;
   wire [0:7]M3, M2, M1, M0;
   assign M3 = 8'b00001111;
   assign M2 = 8'b00111100;
   assign M1 = 8'b01101001;
   assign M0 = {G[0],~G[0],G[0],~G[0],G[0],~G[0], G[0],~G[0]};
   mux8to1 st0(G[3:1], M3, B[3]);
   mux8to1 st1(G[3:1], M2, B[2]);
   mux8to1 st2(G[3:1], M1, B[1]);
   mux8to1 st3(G[3:1], M0, B[0]);
endmodule

Year 2/DSD Lab/week6/lab5p2_tb.v
`timescale 1ns/1ns
`include "lab5p2.v"

module lab5p2_tb;
reg [3:0]G;
wire [3:0]B;

lab5p2 uut(G, B);
initial begin
	
	$dumpfile("lab5p2_tb.vcd");
	$dumpvars(0, lab5p2_tb);
	
	G = 4'b0000;
	#20;
	
	G = 4'b0001;
	#20;
	
	G = 4'b0010;
	#20;
	
	G = 4'b0011;
	#20;
	
	G = 4'b0100;
	#20;
	
	G = 4'b0101;
	#20;
	
	G = 4'b0110;
	#20;
	
	G = 4'b0111;
	#20;
	
	G = 4'b1000;
	#20;
	
	G = 4'b1001;
	#20;
	
	G = 4'b1010;
	#20;
	
	G = 4'b1011;
	#20;
	
	G = 4'b1100;
	#20;
	
	G = 4'b1101;
	#20;
	
	G = 4'b1110;
	#20;
	
	G = 4'b1111;
	#20;
	
	$display("Test Complete");
	$finish;
end
endmodule

Year 2/DSD Lab/week6/lab5p2_tb.vcd
$date
	Mon Sep  4 15:53:27 2023
$end
$version
	Icarus Verilog
$end
$timescale
	1ns
$end
$scope module lab5p2_tb $end
$var wire 4 ! B [3:0] $end
$var reg 4 " G [3:0] $end
$scope module uut $end
$var wire 4 # G [3:0] $end
$var wire 8 $ M1 [0:7] $end
$var wire 8 % M2 [0:7] $end
$var wire 8 & M3 [0:7] $end
$var wire 8 ' M0 [0:7] $end
$var wire 4 ( B [3:0] $end
$scope module st0 $end
$var wire 3 ) s [2:0] $end
$var wire 8 * w [0:7] $end
$var reg 1 + f $end
$upscope $end
$scope module st1 $end
$var wire 3 , s [2:0] $end
$var wire 8 - w [0:7] $end
$var reg 1 . f $end
$upscope $end
$scope module st2 $end
$var wire 3 / s [2:0] $end
$var wire 8 0 w [0:7] $end
$var reg 1 1 f $end
$upscope $end
$scope module st3 $end
$var wire 3 2 s [2:0] $end
$var wire 8 3 w [0:7] $end
$var reg 1 4 f $end
$upscope $end
$upscope $end
$upscope $end
$enddefinitions $end
#0
$dumpvars
04
b1010101 3
b0 2
01
b1101001 0
b0 /
0.
b111100 -
b0 ,
0+
b1111 *
b0 )
b0 (
b1010101 '
b1111 &
b111100 %
b1101001 $
b0 #
b0 "
b0 !
$end
#20
b1 !
b1 (
14
b10101010 '
b10101010 3
b1 "
b1 #
#40
11
b11 !
b11 (
14
b1010101 '
b1010101 3
b1 )
b1 ,
b1 /
b1 2
b10 "
b10 #
#60
b10 !
b10 (
04
b10101010 '
b10101010 3
b11 "
b11 #
#80
b110 !
b110 (
1.
b1010101 '
b1010101 3
b10 )
b10 ,
b10 /
b10 2
b100 "
b100 #
#100
b111 !
b111 (
14
b10101010 '
b10101010 3
b101 "
b101 #
#120
01
b101 !
b101 (
14
b1010101 '
b1010101 3
b11 )
b11 ,
b11 /
b11 2
b110 "
b110 #
#140
b100 !
b100 (
04
b10101010 '
b10101010 3
b111 "
b111 #
#160
1+
b1110 !
b1110 (
11
b1010101 '
b1010101 3
b100 )
b100 ,
b100 /
b100 2
b1000 "
b1000 #
#180
b1111 !
b1111 (
14
b10101010 '
b10101010 3
b1001 "
b1001 #
#200
01
b1101 !
b1101 (
14
b1010101 '
b1010101 3
b101 )
b101 ,
b101 /
b101 2
b1010 "
b1010 #
#220
b1100 !
b1100 (
04
b10101010 '
b10101010 3
b1011 "
b1011 #
#240
b1000 !
b1000 (
0.
b1010101 '
b1010101 3
b110 )
b110 ,
b110 /
b110 2
b1100 "
b1100 #
#260
b1001 !
b1001 (
14
b10101010 '
b10101010 3
b1101 "
b1101 #
#280
11
b1011 !
b1011 (
14
b1010101 '
b1010101 3
b111 )
b111 ,
b111 /
b111 2
b1110 "
b1110 #
#300
b1010 !
b1010 (
04
b10101010 '
b10101010 3
b1111 "
b1111 #
