Year 2/DSD Lab/week6/lab5p1.v
module mux4to1(w,s,f);	
   input [0:3]w;
   input [1:0]s;
   output reg f;
   always @(w or s)
   begin
      if(s==2'b00)
         f = w[0];
      else if(s==2'b01)
              f = w[1];
           else if(s==2'b10)
                   f = w[2];
           	else if(s==2'b11)
                   	f = w[3];
   end
endmodule

module lab5p1(W,f);
   input [0:3]W;
   output f;
   wire [0:3]M;
   assign M[0] = ~W[2]|~W[3];
   assign M[1] = ~W[3];
   assign M[2] = ~W[2]&W[3];
   assign M[3] = ~W[3];
   mux4to1 st0(M, W[0:1], f);
endmodule

Year 2/DSD Lab/week6/lab5p1_tb.v
`timescale 1ns/1ns
`include "lab5p1.v"

module lab5p1_tb;
reg [0:3]W;
wire f;

lab5p1 uut(W, f);
initial begin
	
	$dumpfile("lab5p1.vcd");
	$dumpvars(0, lab5p1_tb);
	
	W = 4'b0000;
	#20;
	
	W = 4'b0001;
	#20;
	
	W = 4'b0010;
	#20;
	
	W = 4'b0011;
	#20;
	
	W = 4'b0100;
	#20;
	
	W = 4'b0101;
	#20;
	
	W = 4'b0110;
	#20;
	
	W = 4'b0111;
	#20;
	
	W = 4'b1000;
	#20;
	
	W = 4'b1001;
	#20;
	
	W = 4'b1010;
	#20;
	
	W = 4'b1011;
	#20;
	
	W = 4'b1100;
	#20;
	
	W = 4'b1101;
	#20;
	
	W = 4'b1110;
	#20;
	
	W = 4'b1111;
	#20;
	
	$display("Test Complete");
	$finish;
end
endmodule

Year 2/DSD Lab/week6/lab5p1.vcd
$date
	Mon Sep  4 14:49:51 2023
$end
$version
	Icarus Verilog
$end
$timescale
	1ns
$end
$scope module lab5p1_tb $end
$var wire 1 ! f $end
$var reg 4 " W [0:3] $end
$scope module uut $end
$var wire 4 # W [0:3] $end
$var wire 1 ! f $end
$var wire 4 $ M [0:3] $end
$scope module st0 $end
$var wire 2 % s [1:0] $end
$var wire 4 & w [0:3] $end
$var reg 1 ! f $end
$upscope $end
$upscope $end
$upscope $end
$enddefinitions $end
#0
$dumpvars
b1101 &
b0 %
b1101 $
b0 #
b0 "
1!
$end
#20
b1010 $
b1010 &
b1 "
b1 #
#40
b1101 $
b1101 &
b10 "
b10 #
#60
0!
b0 $
b0 &
b11 "
b11 #
#80
1!
b1101 $
b1101 &
b1 %
b100 "
b100 #
#100
0!
b1010 $
b1010 &
b101 "
b101 #
#120
1!
b1101 $
b1101 &
b110 "
b110 #
#140
0!
b0 $
b0 &
b111 "
b111 #
#160
b1101 $
b1101 &
b10 %
b1000 "
b1000 #
#180
1!
b1010 $
b1010 &
b1001 "
b1001 #
#200
0!
b1101 $
b1101 &
b1010 "
b1010 #
#220
b0 $
b0 &
b1011 "
b1011 #
#240
1!
b1101 $
b1101 &
b11 %
b1100 "
b1100 #
#260
0!
b1010 $
b1010 &
b1101 "
b1101 #
#280
1!
b1101 $
b1101 &
b1110 "
b1110 #
#300
0!
b0 $
b0 &
b1111 "
b1111 #
