Year 2/DSD Lab/week8/Nreg.v
module Nreg(I, clk, Q);
	parameter n = 8;
	input [n-1:0]I;
	input clk;
	output reg [n-1:0]Q;
	
	always @(posedge clk)
		Q<=I;
endmodule

Year 2/DSD Lab/week8/Nreg_tb.v
`timescale 1ns/1ns
`include "Nreg.v"

module Nreg_tb;
parameter n = 8;
reg [n-1:0]I;
reg clk;
wire [n-1:0]Q;
  
Nreg Nr1(I, clk, Q);
initial begin
	$dumpfile("Nreg_tb.vcd");
	$dumpvars(0, Nreg_tb);
	clk = 0;
	forever #10 clk = ~clk;
end
initial begin
	I = 8'b10101010;
	#20;
	I = 8'b01010101;
	#20;
	I = 8'b11101010;
	#20;
	I = 8'b01011111;
	#20;
	I = 8'b00000000;
	#20;
	I = 8'b01111100;
	#20;
	I = 8'b10000000;
	#20;
	I = 8'b00010001;
	#20;
	$display("Test Complete");
	$finish;
end
endmodule

Year 2/DSD Lab/week8/Nreg_tb.vcd
$date
	Mon Oct  9 15:49:09 2023
$end
$version
	Icarus Verilog
$end
$timescale
	1ns
$end
$scope module Nreg_tb $end
$var wire 8 ! Q [7:0] $end
$var reg 8 " I [7:0] $end
$var reg 1 # clk $end
$scope module Nr1 $end
$var wire 8 $ I [7:0] $end
$var wire 1 # clk $end
$var reg 8 % Q [7:0] $end
$upscope $end
$upscope $end
$enddefinitions $end
#0
$dumpvars
bx %
b10101010 $
0#
b10101010 "
bx !
$end
#10
b10101010 !
b10101010 %
1#
#20
0#
b1010101 "
b1010101 $
#30
b1010101 !
b1010101 %
1#
#40
0#
b11101010 "
b11101010 $
#50
b11101010 !
b11101010 %
1#
#60
0#
b1011111 "
b1011111 $
#70
b1011111 !
b1011111 %
1#
#80
0#
b0 "
b0 $
#90
b0 !
b0 %
1#
#100
0#
b1111100 "
b1111100 $
#110
b1111100 !
b1111100 %
1#
#120
0#
b10000000 "
b10000000 $
#130
b10000000 !
b10000000 %
1#
#140
0#
b10001 "
b10001 $
#150
b10001 !
b10001 %
1#
