Year 2/DSD Lab/week1/example2.v
module example2(x1, x2, x3, f);
input x1, x2, x3;
output f;
and(g,x1,x2);
not(k,x2);
and(h, k, x3);
or(f, g, h);
endmodule

Year 2/DSD Lab/week1/example2_tb.v
`timescale 1ns/1ns
`include "example2.v"

module example2_tb;
reg x1, x2, x3;
wire f;

example2 e2(x1, x2, x3, f);
initial begin
	
	$dumpfile("example2_tb.vcd");
	$dumpvars(0, example2_tb);
	
	x1 = 0;
	x2 = 0;
	x3 = 0;
	#20;
	
	x1 = 0;
	x2 = 1;
	x3 = 0;
	#20;
	
	x1 = 1;
	x2 = 0;
	x3 = 0;
	#20;
	
	x1 = 1;
	x2 = 1;
	x3 = 0;
	#20;
	
	x1 = 0;
	x2 = 0;
	x3 = 1;
	#20;
	
	x1 = 1;
	x2 = 0;
	x3 = 1;
	#20;
	
	x1 = 0;
	x2 = 1;
	x3 = 1;
	#20;
	
	x1 = 1;
	x2 = 1;
	x3 = 1;
	#20;
	
	$display("Test Complete");
end
endmodule

Year 2/DSD Lab/week1/example2_tb.vcd
$date
	Mon Jul 31 15:48:55 2023
$end
$version
	Icarus Verilog
$end
$timescale
	1ns
$end
$scope module example2_tb $end
$var wire 1 ! f $end
$var reg 1 " x1 $end
$var reg 1 # x2 $end
$var reg 1 $ x3 $end
$scope module e2 $end
$var wire 1 ! f $end
$var wire 1 % g $end
$var wire 1 & h $end
$var wire 1 ' k $end
$var wire 1 " x1 $end
$var wire 1 # x2 $end
$var wire 1 $ x3 $end
$upscope $end
$upscope $end
$enddefinitions $end
#0
$dumpvars
1'
0&
0%
0$
0#
0"
0!
$end
#20
0'
1#
#40
1'
0#
1"
#60
1!
1%
0'
1#
#80
1&
1'
0%
1$
0#
0"
#100
1"
#120
0!
0&
0'
1#
0"
#140
1!
1%
1"
