Year 2/DSD Lab/week3/FullAdder.v
module FullAdder(Ci, Xi, Yi, Cout, Si);
input Ci, Xi, Yi;
output Cout, Si;
assign Si = Ci^Xi^Yi;
assign Cout = (Xi&Yi)|(Ci&Yi)|(Ci&Xi);
endmodule

Year 2/DSD Lab/week3/FullAdder_tb.v
`timescale 1ns/1ns
`include "FullAdder.v"

module FullAdder_tb;
reg Ci, Xi, Yi;
wire Cout, Si;

FullAdder F1(Ci, Xi, Yi, Cout, Si);
initial begin
	
	$dumpfile("FullAdder_tb.vcd");
	$dumpvars(0, FullAdder_tb);
	
	Ci = 0;
	Xi = 0;
	Yi = 0;
	#20;
	
	Ci = 0;
	Xi = 0;
	Yi = 1;
	#20;
	
	Ci = 0;
	Xi = 1;
	Yi = 0;
	#20;
	
	Ci = 0;
	Xi = 1;
	Yi = 1;
	#20;
	
	Ci = 1;
	Xi = 0;
	Yi = 0;
	#20;
	
	Ci = 1;
	Xi = 0;
	Yi = 1;
	#20;
	
	Ci = 1;
	Xi = 1;
	Yi = 0;
	#20;
	
	Ci = 1;
	Xi = 1;
	Yi = 1;
	#20;
	
	$display("Test Complete");
end
endmodule

Year 2/DSD Lab/week3/FullAdder_tb.vcd
$date
	Mon Aug 14 15:24:07 2023
$end
$version
	Icarus Verilog
$end
$timescale
	1ns
$end
$scope module FullAdder_tb $end
$var wire 1 ! Si $end
$var wire 1 " Cout $end
$var reg 1 # Ci $end
$var reg 1 $ Xi $end
$var reg 1 % Yi $end
$scope module F1 $end
$var wire 1 # Ci $end
$var wire 1 " Cout $end
$var wire 1 ! Si $end
$var wire 1 $ Xi $end
$var wire 1 % Yi $end
$upscope $end
$upscope $end
$enddefinitions $end
#0
$dumpvars
0%
0$
0#
0"
0!
$end
#20
1!
1%
#40
0%
1$
#60
1"
0!
1%
#80
0"
1!
0%
0$
1#
#100
1"
0!
1%
#120
0%
1$
#140
1!
1%
