Year 2/DSD Lab/week3/FuncDecomp.v
module FuncDecomp(A,B,C,D,f);
input A,B,C,D;
output f;
assign g = (~C&D)|(C&~D);
assign f = (A&g)|(B&~g);
endmodule

Year 2/DSD Lab/week3/FuncDecomp_tb.v
`timescale 1ns/1ns
`include "FuncDecomp.v"

module FuncDecomp_tb;
reg A, B, C, D;
wire f;

FuncDecomp f1(A, B, C, D, f);
initial begin
	
	$dumpfile("FuncDecomp_tb.vcd");
	$dumpvars(0, FuncDecomp_tb);
	
	A = 0;
	B = 0;
	C = 0;
	D = 0;
	#20;
	
	A = 0;
	B = 0;
	C = 0;
	D = 1;
	#20;  
	
	A = 0;
	B = 0;
	C = 1;
	D = 0;
	#20; 
	
	A = 0;
	B = 0;
	C = 1;
	D = 1;
	#20; 
	
	A = 0;
	B = 1;
	C = 0;
	D = 0;
	#20; 
	
	A = 0;
	B = 1;
	C = 0;
	D = 1;
	#20; 
	
	A = 0;
	B = 1;
	C = 1;
	D = 0;
	#20; 
	
	
	A = 0;
	B = 1;
	C = 1;
	D = 1;
	#20; 
	
	
	A = 1;
	B = 0;
	C = 0;
	D = 0;
	#20; 
	
	A = 1;
	B = 0;
	C = 0;
	D = 1;
	#20; 
	
	A = 1;
	B = 0;
	C = 1;
	D = 0;
	#20; 
	
	A = 1;
	B = 0;
	C = 1;
	D = 1;

	#20; 
	
	A = 1;
	B = 1;
	C = 0;
	D = 0;
	#20; 
	
	A = 1;
	B = 1;
	C = 0;
	D = 1;
	#20; 
	
	A = 1;
	B = 1;
	C = 1;
	D = 0;
	#20; 
	
	A = 1;
	B = 1;
	C = 1;
	D = 1;
	#20; 
	$display("Test Complete");
end
endmodule

Year 2/DSD Lab/week3/FuncDecomp_tb.vcd
$date
	Mon Aug 14 14:16:05 2023
$end
$version
	Icarus Verilog
$end
$timescale
	1ns
$end
$scope module FuncDecomp_tb $end
$var wire 1 ! f $end
$var reg 1 " A $end
$var reg 1 # B $end
$var reg 1 $ C $end
$var reg 1 % D $end
$scope module f1 $end
$var wire 1 " A $end
$var wire 1 # B $end
$var wire 1 $ C $end
$var wire 1 % D $end
$var wire 1 ! f $end
$var wire 1 & g $end
$upscope $end
$upscope $end
$enddefinitions $end
#0
$dumpvars
0&
0%
0$
0#
0"
0!
$end
#20
1&
1%
#40
0%
1$
#60
0&
1%
#80
1!
0%
0$
1#
#100
0!
1&
1%
#120
0%
1$
#140
1!
0&
1%
#160
0!
0%
0$
0#
1"
#180
1!
1&
1%
#200
0%
1$
#220
0!
0&
1%
#240
1!
0%
0$
1#
#260
1&
1%
#280
0%
1$
#300
0&
1%
