Year 2/DSD Lab/week7/jkFF.v
module jkFF(j, k, clk, reset, q);
   input j,k,clk,reset;
   output reg q;

   always @(posedge clk)
   begin
   	if(reset)
   	   q <= 0;
   	else
   	begin
   	   if(!q)
   	   begin 
   	      if(j)
   	         q<=1;
   	   end
   	   else
   	   begin
   	      if(k)
   	         q<=0;
   	   end
   	end
    end
endmodule

Year 2/DSD Lab/week7/jkFF_tb.v
`timescale 1ns/1ns
`include "jkFF.v"

module jkFF_tb;
reg j,k,clk,reset;
wire q;

jkFF jkFFq(j,k,clk,reset,q);
initial begin
    $dumpfile("jkFF_tb.vcd");
    $dumpvars(0,jkFF_tb);
    clk = 1;
    forever #20 clk = ~clk;
end
initial begin
    j=0;k=0;reset=1;#10;
    j=0;k=0;reset=0;#20;
    j=1;k=0;reset=0;#20;
    j=0;k=1;reset=0;#20;
    j=1;k=1;reset=0;#20;
    j=0;k=0;reset=1;#20;
    j=0;k=0;reset=0;#10;
    $display("Test Complete");
    $finish;
end
endmodule

Year 2/DSD Lab/week7/jkFF_tb.vcd
$date
	Mon Sep 18 15:37:33 2023
$end
$version
	Icarus Verilog
$end
$timescale
	1ns
$end
$scope module jkFF_tb $end
$var wire 1 ! q $end
$var reg 1 " clk $end
$var reg 1 # j $end
$var reg 1 $ k $end
$var reg 1 % reset $end
$scope module jkFFq $end
$var wire 1 " clk $end
$var wire 1 # j $end
$var wire 1 $ k $end
$var wire 1 % reset $end
$var reg 1 ! q $end
$upscope $end
$upscope $end
$enddefinitions $end
#0
$dumpvars
1%
0$
0#
1"
0!
$end
#10
0%
#20
0"
#30
1#
#40
1!
1"
#50
1$
0#
#60
0"
#70
1#
#80
0!
1"
#90
1%
0$
0#
#100
0"
#110
0%
