Year 2/DSD Lab/week7/srFF.v
module srFF(s, r, clk, reset, q);
   input s,r,clk,reset;
   output reg q;

   always @(negedge clk)
   begin
   	if(reset)
   	   q <= 0;
   	else
   	begin
   	   if(s==0 && r==1)
   	      q = 0;
   	   if(s==1 && r==0)
   	      q = 1;
   	end
    end
endmodule

Year 2/DSD Lab/week7/srFF_tb.v
`timescale 1ns/1ns
`include "srFF.v"

module srFF_tb;
reg s,r,clk,reset;
wire q;

srFF srFFq(s,r,clk,reset,q);
initial begin
    $dumpfile("srFF_tb.vcd");
    $dumpvars(0,srFF_tb);
    clk = 1;
    forever #20 clk = ~clk;
end
initial begin
    s=0;r=0;reset=1;#10;
    s=0;r=0;reset=0;#20;
    s=1;r=0;reset=0;#20;
    s=0;r=1;reset=0;#20;
    s=1;r=1;reset=0;#20;
    s=0;r=0;reset=1;#20;
    s=0;r=0;reset=0;#10;
    $display("Test Complete");
    $finish;
end
endmodule

Year 2/DSD Lab/week7/srFF_tb.vcd
$date
	Mon Sep 18 16:15:37 2023
$end
$version
	Icarus Verilog
$end
$timescale
	1ns
$end
$scope module srFF_tb $end
$var wire 1 ! q $end
$var reg 1 " clk $end
$var reg 1 # r $end
$var reg 1 $ reset $end
$var reg 1 % s $end
$scope module srFFq $end
$var wire 1 " clk $end
$var wire 1 # r $end
$var wire 1 $ reset $end
$var wire 1 % s $end
$var reg 1 ! q $end
$upscope $end
$upscope $end
$enddefinitions $end
#0
$dumpvars
0%
1$
0#
1"
x!
$end
#10
0$
#20
0"
#30
1%
#40
1"
#50
1#
0%
#60
0!
0"
#70
1%
#80
1"
#90
1$
0#
0%
#100
0"
#110
0$
