Year 2/DSD Lab/week4/Mux16_1.v
module Mux8_1(w,s,f);
input [0:7]w;
input [2:0]s;
output reg f;
always @(w or s)
case(s)
3'b000: f = w[0];
3'b001: f = w[1];
3'b010: f = w[2];
3'b011: f = w[3];
3'b100: f = w[4];
3'b101: f = w[5];
3'b110: f = w[6];
3'b111: f = w[7];
endcase
endmodule

module Mux2_1(w,s,f);
input [0:1]w;
input s;
output reg f;
always @(w or s)
case(s)
0: f = w[0];
1: f = w[1];
endcase
endmodule

module Mux16_1(w,s,f);
input [0:15]w;
input [3:0]s;
output f;
wire [0:1]m;
Mux8_1 mux1(w[0:7], s[2:0], m[0]);
Mux8_1 mux2(w[8:15], s[2:0], m[1]);
Mux2_1 mux3(m[0:1], s[3], f);
endmodule

Year 2/DSD Lab/week4/Mux16_1_tb.v
`timescale 1ns/1ns
`include "Mux16_1.v"

module Mux16_1_tb;
reg [0:15]w;
reg [3:0]s;
wire f;

Mux16_1 M2(w, s, f);
initial begin
	
	$dumpfile("Mux16_1_tb.vcd");
	$dumpvars(0, Mux16_1_tb);
	
	w = 16'b0000000000000001;
	s = 4'b0000;
	#20;
	
	w = 16'b0000000000000001;
	s = 4'b1111;
	#20;
	
	w = 16'b0000000000000100;
	s = 4'b0010;
	#20;
	
	w = 16'b0010000000000000;
	s = 4'b1101;
	#20;	
	
	w = 16'b0010000000000000;
	s = 4'b0010;
	#20;
	
	w = 16'b0000000000000100;
	s = 4'b1101;
	#20;
	
	w = 16'b1000000000000000;
	s = 4'b0000;
	#20;
	
	w = 16'b0000010000000000;
	s = 4'b0101;
	#20;
	
	$display("Test Complete");
	$finish;
end
endmodule

Year 2/DSD Lab/week4/Mux16_1_tb.vcd
$date
	Mon Aug 21 14:56:34 2023
$end
$version
	Icarus Verilog
$end
$timescale
	1ns
$end
$scope module Mux16_1_tb $end
$var wire 1 ! f $end
$var reg 4 " s [3:0] $end
$var reg 16 # w [0:15] $end
$scope module M2 $end
$var wire 4 $ s [3:0] $end
$var wire 16 % w [0:15] $end
$var wire 2 & m [0:1] $end
$var wire 1 ! f $end
$scope module mux1 $end
$var wire 3 ' s [2:0] $end
$var wire 8 ( w [0:7] $end
$var reg 1 ) f $end
$upscope $end
$scope module mux2 $end
$var wire 3 * s [2:0] $end
$var wire 8 + w [0:7] $end
$var reg 1 , f $end
$upscope $end
$scope module mux3 $end
$var wire 1 - s $end
$var wire 2 . w [0:1] $end
$var reg 1 ! f $end
$upscope $end
$upscope $end
$upscope $end
$enddefinitions $end
#0
$dumpvars
b0 .
0-
0,
b1 +
b0 *
0)
b0 (
b0 '
b0 &
b1 %
b0 $
b1 #
b0 "
0!
$end
#20
1!
b1 &
b1 .
1,
b111 '
b111 *
1-
b1111 "
b1111 $
#40
0!
b0 &
b0 .
0,
b10 '
b10 *
0-
b100 +
b10 "
b10 $
b100 #
b100 %
#60
b101 '
b101 *
1-
b100000 (
b0 +
b1101 "
b1101 $
b10000000000000 #
b10000000000000 %
#80
1!
b10 &
b10 .
1)
b10 '
b10 *
0-
b10 "
b10 $
#100
0)
b1 &
b1 .
1,
b101 '
b101 *
1-
b0 (
b100 +
b1101 "
b1101 $
b100 #
b100 %
#120
1)
b10 &
b10 .
0,
b0 '
b0 *
0-
b10000000 (
b0 +
b0 "
b0 $
b1000000000000000 #
b1000000000000000 %
#140
b101 '
b101 *
b100 (
b101 "
b101 $
b10000000000 #
b10000000000 %
