Year 2/DSD Lab/week9/p1.v
module dff(d,q,clk,reset);
input clk,d,reset;
output reg q;
always @ (posedge clk or posedge reset)begin
if(reset)q<=1'b0;
else q<=d;
end 
endmodule

module p1(clk,x,y,reset,lo);
input clk,x,reset;
output y;
output [2:0]lo;
wire [2:0]li,s;
assign s[2]=(~lo[0]&~x&lo[1])|(~x&lo[2]);
assign s[1]=(~lo[2]&~x&~lo[1]&~lo[0])|(x&lo[0])|(~x&lo[0]);
assign s[0]=(~lo[2]&~lo[1]&~lo[0])|(lo[1]&lo[0]);
dff st0(s[2],lo[2],clk,reset);
dff st1(s[1],lo[1],clk,reset);
dff st2(s[0],lo[0],clk,reset);
assign y=(lo[2]&x)|(lo[1]&~x)|(lo[1]&lo[0]);
assign lo=li;
endmodule

Year 2/DSD Lab/week9/p1_tb.v
`timescale 1ns/1ns
`include "p1.v"
module p1_tb;
reg clk,x,reset;
wire y;
wire[2:0]lo;
p1 uut(clk,x,y,reset,lo);
initial begin
clk=0;
forever #10 clk=~clk;
end 

  initial begin
  $dumpfile("p1_tb.vcd");
  $dumpvars(0,p1_tb);
     x=0;reset=1;#20
     x=1;reset=0;#20
     x=0;#20
     x=1;#20
     x=0;#30
     x=1;#40
     x=0;#40
     x=1;#20
     x=0;#40
       $display("test complete");
       $finish;
       
    end 
    endmodule

Year 2/DSD Lab/week9/p1_tb.vcd
$date
	Mon Oct 16 16:00:09 2023
$end
$version
	Icarus Verilog
$end
$timescale
	1ns
$end
$scope module p1_tb $end
$var wire 3 ! lo [2:0] $end
$var wire 1 " y $end
$var reg 1 # clk $end
$var reg 1 $ reset $end
$var reg 1 % x $end
$scope module uut $end
$var wire 1 # clk $end
$var wire 3 & li [2:0] $end
$var wire 3 ' lo [2:0] $end
$var wire 1 $ reset $end
$var wire 1 % x $end
$var wire 1 " y $end
$var wire 3 ( s [2:0] $end
$scope module st0 $end
$var wire 1 # clk $end
$var wire 1 ) d $end
$var wire 1 $ reset $end
$var reg 1 * q $end
$upscope $end
$scope module st1 $end
$var wire 1 # clk $end
$var wire 1 + d $end
$var wire 1 $ reset $end
$var reg 1 , q $end
$upscope $end
$scope module st2 $end
$var wire 1 # clk $end
$var wire 1 - d $end
$var wire 1 $ reset $end
$var reg 1 . q $end
$upscope $end
$upscope $end
$upscope $end
$enddefinitions $end
#0
$dumpvars
0.
1-
0,
1+
0*
0)
b11 (
b0 '
bz &
0%
1$
0#
0"
b0 !
$end
#10
1#
#20
0+
b1 (
0#
0$
1%
#30
1+
0-
b10 (
b1 !
b1 '
1.
1#
#40
0#
0%
#50
1)
0+
1"
b100 (
0.
b10 !
b10 '
1,
1#
#60
0)
b0 (
0"
0#
1%
#70
1-
b1 (
b0 !
b0 '
0,
1#
#80
1+
b11 (
0#
0%
#90
0)
b11 (
1"
1.
b11 !
b11 '
1,
1#
#100
0#
#110
1#
1%
#120
0#
#130
1#
#140
0#
#150
1#
0%
#160
0#
#170
1#
#180
0#
#190
1#
1%
#200
0#
#210
1#
0%
