Year 2/DSD Lab/week9/p2.v
module tFF(t,q,clk,reset);
input clk,t,reset;
output reg q;
always @(posedge clk or posedge reset)begin
if(reset)q<=1'b0;
else begin
if(t==1'b0)q<=q;
else q<=~q;
end
end
endmodule
module p2(clk,x,reset,A,B);
input clk,x,reset;
output A,B;
wire[1:0]s;
assign s[1]=(B&~x)|(~A&B);
assign s[0]=(A&~x)|(~B&~x)|(~A&B&x);
tFF st0(s[1],A,clk,reset);
tFF st1(s[0],B,clk,reset);
endmodule

Year 2/DSD Lab/week9/p2_tb.v
`timescale 1ns/1ns
`include"p2.v"
module p2_tb;
reg clk,x,reset;
wire A,B;
p2 out(clk,x,reset,A,B);
initial begin
clk=1;
forever#10 clk=~clk;
end
initial begin
$dumpfile("p2_tb.vcd");
$dumpvars(0,p2_tb);
x=0;reset=1;#20;
x=1;reset=0;#20;
x=0;#40;
x=1;#20;
x=0;#20;
x=1;#20;
$display("Test Completed");
$finish;
end endmodule

Year 2/DSD Lab/week9/p2_tb.vcd
$date
	Mon Oct 16 15:46:44 2023
$end
$version
	Icarus Verilog
$end
$timescale
	1ns
$end
$scope module p2_tb $end
$var wire 1 ! B $end
$var wire 1 " A $end
$var reg 1 # clk $end
$var reg 1 $ reset $end
$var reg 1 % x $end
$scope module out $end
$var wire 1 # clk $end
$var wire 1 $ reset $end
$var wire 1 % x $end
$var wire 2 & s [1:0] $end
$var wire 1 ! B $end
$var wire 1 " A $end
$scope module st0 $end
$var wire 1 # clk $end
$var wire 1 $ reset $end
$var wire 1 ' t $end
$var reg 1 " q $end
$upscope $end
$scope module st1 $end
$var wire 1 # clk $end
$var wire 1 $ reset $end
$var wire 1 ( t $end
$var reg 1 ! q $end
$upscope $end
$upscope $end
$upscope $end
$enddefinitions $end
#0
$dumpvars
1(
0'
b1 &
0%
1$
1#
0"
0!
$end
#10
0#
#20
1'
1!
1(
b11 &
1#
0$
1%
#30
0#
#40
0'
1"
0!
1(
b1 &
1#
0%
#50
0#
#60
1'
b11 &
1!
1#
#70
0#
#80
0"
0!
0(
0'
b0 &
1#
1%
#90
0#
#100
1(
b1 &
1#
0%
#110
0#
#120
1'
1!
1(
b11 &
1#
1%
#130
0#
#140
0(
0'
b0 &
0!
1"
1#
